undidPyjl/__init__.py
undidPyjl/julia_management.py
undidPyjl/stageone.py
undidPyjl/stagethree.py
undidPyjl/stagetwo.py
undidPyjl-0.1.2.dist-info/LICENSE
undidPyjl-0.1.2.dist-info/METADATA
undidPyjl-0.1.2.dist-info/WHEEL
undidPyjl-0.1.2.dist-info/top_level.txt
undidPyjl-0.1.2.dist-info/RECORD
